webscrppandas/web2pd.py
web2pandas-1.0.0.dist-info/LICENSE
web2pandas-1.0.0.dist-info/METADATA
web2pandas-1.0.0.dist-info/WHEEL
web2pandas-1.0.0.dist-info/entry_points.txt
web2pandas-1.0.0.dist-info/top_level.txt
web2pandas-1.0.0.dist-info/RECORD
